msmanager/__init__.py
msmanager/__main__.py
msmanager/cli.py
msmanager/config.py
msmanager/exceptions.py
msmanager/functions.py
msmanager/models.py
msmanager/msm.py
msmanager/types.py
msmanager/units.py
msmanager-0.4.6.dist-info/LICENSE
msmanager-0.4.6.dist-info/METADATA
msmanager-0.4.6.dist-info/WHEEL
msmanager-0.4.6.dist-info/RECORD
