Metadata-Version: 2.1
Name: msmanager
Version: 0.4.6
Summary: Manager for managing Mindustry servers.
License: MIT
Author: Romanin
Author-email: semina054@gmail.com
Requires-Python: >=3.9,<3.12
Classifier: License :: OSI Approved :: MIT License
Classifier: Operating System :: Microsoft :: Windows
Classifier: Operating System :: POSIX :: Linux
Classifier: Programming Language :: Python :: 3
Classifier: Programming Language :: Python :: 3.9
Classifier: Programming Language :: Python :: 3.10
Classifier: Programming Language :: Python :: 3.11
Requires-Dist: click (>=8)
Requires-Dist: platformdirs (>=3.5.1)
Requires-Dist: pydantic (>=1.10.7)
Requires-Dist: pydustry-py (>=2)
Requires-Dist: rich (>=13.3)
Requires-Dist: screens-py (>=0.5)
Requires-Dist: vbml (>=1.1.post1)
Requires-Dist: versioner.py (>=1.1.0)
